genebench/__init__.py
genebench/benchmark.py
genebench/datatypes.py
genebench/generatesilico.py
genebench/geoimporter.py
genebench/startup.py
genebench/utils.py
genebench/validationdataimporter.py
genebench/diffmethods/__init__.py
genebench/diffmethods/chdir.py
genebench/diffmethods/chdirpy.py
genebench/diffmethods/diffmethodsmanager.py
genebench/diffmethods/limma.py
genebench/diffmethods/random.py
genebench/diffmethods/sam.py
genebench/diffmethods/ttest.py
genebench/diffmethods/MIDGET/__init__.py
genebench/diffmethods/MIDGET/common.py
genebench/diffmethods/MIDGET/neural.py
genebench/diffmethods/MIDGET/xgb.py
genebench/diffmethods/base/__init__.py
genebench/diffmethods/base/diffmethod.py
genebench/diffmethods/base/rdiffmethod.py
genebench/diffmethods/base/R/characteristic_direction.r
genebench/diffmethods/base/R/limma.r
genebench/diffmethods/base/R/sam.r
genebench/evaluationmetrics/__init__.py
genebench/evaluationmetrics/base.py
genebench/evaluationmetrics/f1.py
genebench/evaluationmetrics/kolmogorov.py
genebench/evaluationmetrics/metricmanager.py
genebench/evaluationmetrics/roc.py
genebench/silico/__init__.py
genebench/silico/silicogeneratorsmanager.py
genebench/silico/generators/__init__.py
genebench/silico/generators/base.py
genebench/silico/generators/linear.py
genebench/storage/__init__.py
genebench/storage/storage.py
genebench/storage/storageprovider.py
genebench/storage/storageproviderfilesystem.py
genebench/storage/storageprovidermongo.py
genebench-0.0.4.dist-info/LICENSE
genebench-0.0.4.dist-info/METADATA
genebench-0.0.4.dist-info/WHEEL
genebench-0.0.4.dist-info/top_level.txt
genebench-0.0.4.dist-info/RECORD
