Metadata-Version: 2.1
Name: genebench
Version: 0.0.4
Summary: Benchmark-ing framework used in analyzing methods that detect deferentially expressed genes from biological samples
Home-page: https://github.com/raduangelescu/GeneBench
Author: Radu Angelescu
Author-email: raduangelescu@gmail.com
License: UNKNOWN
Project-URL: Bug Tracker, https://github.com/raduangelescu/GeneBench/issues
Platform: UNKNOWN
Classifier: Programming Language :: Python :: 3
Classifier: License :: OSI Approved :: MIT License
Classifier: Operating System :: OS Independent
Requires-Python: >=3.8
Requires-Dist: GEOparse
Requires-Dist: matplotlib
Requires-Dist: numpy (==1.19.2)
Requires-Dist: pandas
Requires-Dist: pymongo
Requires-Dist: rpy2
Requires-Dist: scipy
Requires-Dist: sklearn
Requires-Dist: tensorflow-gpu
Requires-Dist: xgboost
